scripts/__init__.py
scripts/routegen
scripts/snap-version
scripts/snapconfig
scripts/uwsgen
snap/__init__.py
snap/cli_tools.py
snap/common.py
snap/config_templates.py
snap/constants.py
snap/core.py
snap/csvutils.py
snap/decoders.py
snap/loggers.py
snap/logging_config.yaml
snap/metaobjects.py
snap/ngen.py
snap/snap.py
snap/testutils.py
snap_micro-1.0.8.data/scripts/routegen
snap_micro-1.0.8.data/scripts/snap-version
snap_micro-1.0.8.data/scripts/snapconfig
snap_micro-1.0.8.data/scripts/uwsgen
tests/__init__.py
tests/context.py
tests/snapcon.py
tests/test_application.py
tests/test_config_parsing.py
tests/test_routegen.py
tests/testbed_decode.py
tests/testbed_services.py
tests/testbed_transforms.py
tests/testbed_validate.py
snap_micro-1.0.8.dist-info/LICENSE
snap_micro-1.0.8.dist-info/METADATA
snap_micro-1.0.8.dist-info/WHEEL
snap_micro-1.0.8.dist-info/top_level.txt
snap_micro-1.0.8.dist-info/RECORD
