Metadata-Version: 2.1
Name: snap-micro
Version: 1.0.8
Summary: Small Network Applications in Python: a microservices toolkit
Home-page: http://github.com/binarymachines/snap
Author: Dexter Taylor
Author-email: binarymachineshop@gmail.com
License: MIT
Keywords: microservices web framework
Platform: any
Classifier: Development Status :: 4 - Beta
Classifier: License :: OSI Approved :: MIT License
Classifier: Programming Language :: Python
Classifier: Topic :: Software Development
License-File: LICENSE
Requires-Dist: docopt
Requires-Dist: Flask
Requires-Dist: flask-cors
Requires-Dist: itsdangerous
Requires-Dist: Jinja2
Requires-Dist: MarkupSafe
Requires-Dist: PyYAML
Requires-Dist: Werkzeug
Requires-Dist: requests
